prevectorchunks_core/__init__.py
prevectorchunks_core/test_loader.py
prevectorchunks_core/config/__init__.py
prevectorchunks_core/config/splitter_config.py
prevectorchunks_core/migrations/__init__.py
prevectorchunks_core/os-llm/__init__.py
prevectorchunks_core/os-llm/llava.py
prevectorchunks_core/rlchunker/__init__.py
prevectorchunks_core/rlchunker/env.py
prevectorchunks_core/rlchunker/inference.py
prevectorchunks_core/rlchunker/model.py
prevectorchunks_core/rlchunker/reward.py
prevectorchunks_core/rlchunker/savepretrained.py
prevectorchunks_core/rlchunker/testpretrained.py
prevectorchunks_core/rlchunker/utils.py
prevectorchunks_core/rlchunker/pretrained/__init__.py
prevectorchunks_core/rlchunker/pretrained/model_info.txt
prevectorchunks_core/rlchunker/pretrained/policy_model.pt
prevectorchunks_core/services/DocuToImageConverter.py
prevectorchunks_core/services/DocuToMarkdownExtractor.py
prevectorchunks_core/services/__init__.py
prevectorchunks_core/services/audio_processor.py
prevectorchunks_core/services/chunk_documents_crud_vdb.py
prevectorchunks_core/services/chunk_to_all_content_mapper.py
prevectorchunks_core/services/image_processor.py
prevectorchunks_core/services/markdown_and_chunk_documents.py
prevectorchunks_core/services/propositional_index.py
prevectorchunks_core/services/video_analyser.py
prevectorchunks_core/tests/__init__.py
prevectorchunks_core/tests/test_local.py
prevectorchunks_core/utils/__init__.py
prevectorchunks_core/utils/extract_content.py
prevectorchunks_core/utils/file_loader.py
prevectorchunks_core/utils/llm_wrapper.py
prevectorchunks_core-0.1.39.dist-info/licenses/LICENCE
prevectorchunks_core-0.1.39.dist-info/licenses/LICENSE
prevectorchunks_core-0.1.39.dist-info/METADATA
prevectorchunks_core-0.1.39.dist-info/WHEEL
prevectorchunks_core-0.1.39.dist-info/top_level.txt
prevectorchunks_core-0.1.39.dist-info/RECORD
