Metadata-Version: 2.4
Name: prevectorchunks-core
Version: 0.1.39
Summary: A Python module that allows conversion of a document into chunks to be inserted into Pinecone vector database
Author-email: Zul Al-Kabir <zul.developer.2023@gmail.com>
License: MIT License
Project-URL: Homepage, https://github.com/zuldeveloper2023/PreVectorChunks
Project-URL: Source, https://github.com/zuldeveloper2023/PreVectorChunks
Requires-Python: <3.12,>=3.7
License-File: LICENCE
License-File: LICENSE
Requires-Dist: packaging~=24.1
Requires-Dist: openai<3.0.0,>=2.6.0
Requires-Dist: python-dotenv~=1.0.1
Requires-Dist: PyJWT~=2.7.0
Requires-Dist: fastapi~=0.112.2
Requires-Dist: datasets~=4.1.0
Requires-Dist: pinecone~=7.3.0
Requires-Dist: pytesseract~=0.3.13
Requires-Dist: python-docx~=1.2.0
Requires-Dist: PyPDF2~=3.0.1
Requires-Dist: pillow~=11.3.0
Requires-Dist: torch~=2.2.2
Requires-Dist: torchvision~=0.17.2
Requires-Dist: torchaudio~=2.2.2
Requires-Dist: sentence-transformers~=5.1.1
Requires-Dist: py-gutenberg~=1.0.3
Requires-Dist: langchain-text-splitters~=0.3.11
Requires-Dist: langchain~=0.3
Requires-Dist: langchain_openai~=0.3.35
Requires-Dist: accelerate>=0.22.0
Requires-Dist: pathlib~=1.0.1
Requires-Dist: transformers~=4.57.0
Requires-Dist: imageio-ffmpeg~=0.6.0
Requires-Dist: opencv-python~=4.8.0.76
Requires-Dist: requests~=2.32.5
Requires-Dist: langchain-core~=0.3.78
Requires-Dist: pdf2image~=1.17.0
Requires-Dist: docx2pdf~=0.1.8
Requires-Dist: numpy~=1.23.5
Requires-Dist: scikit-learn~=1.7.2
Requires-Dist: PyMuPDF~=1.22.5
Requires-Dist: pypandoc~=1.13
Requires-Dist: reportlab~=4.1.0
Requires-Dist: weasyprint~=62.0
Requires-Dist: lxml~=4.9.3
Requires-Dist: cssselect2~=0.7.0
Requires-Dist: cairocffi~=1.4.0
Requires-Dist: tensorflow~=2.12.0
Requires-Dist: pandas~=2.2.2
Requires-Dist: openpyxl~=3.1.2
Requires-Dist: python-pptx~=0.6.21
Dynamic: license-file
